lemonsqueezer/__init__.py
lemonsqueezer/lemonsqueezer.py
lemonsqueezer/modules.py
lemonsqueezer/util.py
lemonsqueezer-0.1.4.dist-info/METADATA
lemonsqueezer-0.1.4.dist-info/RECORD
lemonsqueezer-0.1.4.dist-info/WHEEL
lemonsqueezer-0.1.4.dist-info/top_level.txt
