Metadata-Version: 2.1
Name: lemonsqueezer
Version: 0.1.4
Summary: An fast and lightweight wrapper for lemonbar
Home-page: https://gitlab.com/michalis_pardalos/lemonsqueezer
Author: Michalis Pardalos
Author-email: mpardalos@gmail.com
License: MIT
Platform: UNKNOWN
Classifier: License :: OSI Approved :: MIT License
Classifier: Programming Language :: Python
Classifier: Programming Language :: Python :: 3
Classifier: Programming Language :: Python :: 3.5
Classifier: Programming Language :: Python :: Implementation :: CPython
Requires-Python: >=3.6.0
